README.md
setup.cfg
setup.py
console_chat/__init__.py
console_chat/client.py
console_chat/server.py
console_chat.egg-info/PKG-INFO
console_chat.egg-info/SOURCES.txt
console_chat.egg-info/dependency_links.txt
console_chat.egg-info/top_level.txt