Metadata-Version: 2.1
Name: console-chat
Version: 1.0.1
Summary: Simple console chat
Home-page: UNKNOWN
Author: chevychelov.n
License: UNKNOWN
Platform: UNKNOWN
Classifier: Operating System :: POSIX :: Linux
Classifier: Programming Language :: Python :: 3.9
